tap_postgres/__init__.py
tap_postgres/client.py
tap_postgres/tap.py
meltanolabs_tap_postgres-0.7.4.dist-info/METADATA
meltanolabs_tap_postgres-0.7.4.dist-info/WHEEL
meltanolabs_tap_postgres-0.7.4.dist-info/entry_points.txt
meltanolabs_tap_postgres-0.7.4.dist-info/licenses/LICENSE
meltanolabs_tap_postgres-0.7.4.dist-info/RECORD
