Metadata-Version: 2.4
Name: meltanolabs-tap-postgres
Version: 0.7.4
Summary: Singer tap for Postgres, built with the Meltano SDK for Singer Targets.
Project-URL: Homepage, https://meltano.com
Project-URL: Repository, https://github.com/MeltanoLabs/tap-postgres
Project-URL: Documentation, https://github.com/MeltanoLabs/tap-postgres/blob/main/README.md
Author-email: Meltano Team and Contributors <hello@meltano.com>
Maintainer-email: Meltano Team and Contributors <hello@meltano.com>
License-Expression: Elastic-2.0
License-File: LICENSE
Keywords: ELT,Meltano,Meltano SDK,Postgres,Singer
Classifier: Intended Audience :: Developers
Classifier: Operating System :: OS Independent
Classifier: Programming Language :: Python :: 3.10
Classifier: Programming Language :: Python :: 3.11
Classifier: Programming Language :: Python :: 3.12
Classifier: Programming Language :: Python :: 3.13
Classifier: Programming Language :: Python :: 3.14
Classifier: Programming Language :: Python :: Implementation :: CPython
Requires-Python: >=3.10
Requires-Dist: paramiko>=4
Requires-Dist: psycopg2-binary==2.9.11
Requires-Dist: singer-sdk[faker,sql]~=0.53.0
Requires-Dist: sqlalchemy==2.0.45
Provides-Extra: msgspec
Requires-Dist: msgspec>=0.19.0; extra == 'msgspec'
